ssd_project/__init__.py
ssd_project/functions/__init__.py
ssd_project/functions/detection.py
ssd_project/functions/multiboxloss.py
ssd_project/model/__init__.py
ssd_project/model/ssd.py
ssd_project/utils/__init__.py
ssd_project/utils/global_variables.py
ssd_project/utils/helpers.py
ssd_project/utils/metrics.py
ssd_project/utils/transformations.py
ssd_project/utils/utils.py
ssd_project-1.1.dist-info/LICENSE
ssd_project-1.1.dist-info/METADATA
ssd_project-1.1.dist-info/WHEEL
ssd_project-1.1.dist-info/top_level.txt
ssd_project-1.1.dist-info/RECORD
