Metadata-Version: 2.1
Name: ssd-project
Version: 1.1
Summary: Single Shot MultiBox Detector - SSD
Home-page: https://github.com/ilijagjorgjiev/SSD_FascadeParsing
Author: Ilija Gjorgjiev
Author-email: ilija.gjorgjiev@epfl.ch
License: UNKNOWN
Platform: UNKNOWN
Classifier: Programming Language :: Python :: 3
Classifier: License :: OSI Approved :: MIT License
